pygeopkg/__init__.py
pygeopkg/conversion/__init__.py
pygeopkg/conversion/to_geopkg_geom.py
pygeopkg/conversion/to_wkb.py
pygeopkg/core/__init__.py
pygeopkg/core/field.py
pygeopkg/core/geopkg.py
pygeopkg/core/srs.py
pygeopkg/core/utils.py
pygeopkg/resources/__init__.py
pygeopkg/resources/gpkg_sql.py
pygeopkg/shared/__init__.py
pygeopkg/shared/constants.py
pygeopkg/shared/enumeration.py
pygeopkg/shared/messages.py
pygeopkg/shared/sql.py
pygeopkg-0.1.3.dist-info/LICENSE
pygeopkg-0.1.3.dist-info/METADATA
pygeopkg-0.1.3.dist-info/WHEEL
pygeopkg-0.1.3.dist-info/top_level.txt
pygeopkg-0.1.3.dist-info/RECORD
