Metadata-Version: 2.1
Name: pygeopkg
Version: 0.1.3
Summary: A Python library that allows for the creation and population of OGC GeoPackage databases with write access.
Home-page: https://github.com/realiii/pygeopkg
Author: Integrated Informatics Inc.
Author-email: "Integrated Informatics Inc." <contact@integrated-informatics.com>
License: Copyright 2019, Integrated Informatics Inc.
Project-URL: Homepage, https://github.com/realiii/pygeopkg
Keywords: geopackage
Classifier: Programming Language :: Python
Classifier: Programming Language :: Python :: 2
Classifier: Programming Language :: Python :: 3
Classifier: License :: OSI Approved :: MIT License
Classifier: Operating System :: OS Independent
Classifier: License :: OSI Approved :: MIT License
Classifier: Operating System :: OS Independent
License-File: LICENSE
Provides-Extra: dev
Requires-Dist: pytest ; extra == 'dev'
Requires-Dist: coverage ; extra == 'dev'
Requires-Dist: twine ; extra == 'dev'
Requires-Dist: build ; extra == 'dev'
